flow_3d/__init__.py
flow_3d-0.0.0.dist-info/METADATA
flow_3d-0.0.0.dist-info/WHEEL
flow_3d-0.0.0.dist-info/RECORD
