Metadata-Version: 2.4
Name: flow-3d
Version: 0.0.0
Author-email: Peter Pak <ppak10@gmail.com>
Requires-Python: >=3.10
Requires-Dist: hatch>=1.14.1
